treedecomp.py
treedecomp-1.2.0.dist-info/LICENSE.txt
treedecomp-1.2.0.dist-info/METADATA
treedecomp-1.2.0.dist-info/WHEEL
treedecomp-1.2.0.dist-info/top_level.txt
treedecomp-1.2.0.dist-info/RECORD
