Metadata-Version: 2.1
Name: treedecomp
Version: 1.2.0
Summary: Python Class for Tree Decomposition
Home-page: https://gitlab.inria.fr/amibio/treedecomp
Author: Sebastian Will
Author-email: sebastian.will@polytechnique.edu
Maintainer: Sebastian Will
Maintainer-email: sebastian.will@polytechnique.edu
Classifier: Development Status :: 5 - Production/Stable
Classifier: Intended Audience :: Science/Research
Classifier: Intended Audience :: Developers
Classifier: License :: OSI Approved :: GNU General Public License v3 (GPLv3)
Classifier: Programming Language :: Python :: 3
Classifier: Programming Language :: Python :: 3 :: Only
Classifier: Topic :: Scientific/Engineering
Classifier: Operating System :: OS Independent
Requires-Python: >=3.6
License-File: LICENSE.txt
